zyntex/__init__.py
zyntex/code_generation/__init__.py
zyntex/code_generation/configuration.py
zyntex/code_generation/printer.py
zyntex/code_generation/premade/__init__.py
zyntex/code_generation/premade/default_printer.py
zyntex/code_generation/premade/function_printer.py
zyntex/code_generation/premade/source_code_printer.py
zyntex/code_generation/premade/source_file_printer.py
zyntex/code_generation/premade/test_printer.py
zyntex/code_generation/premade/type_printer.py
zyntex/code_generation/premade/variable_printer.py
zyntex/parsing/__init__.py
zyntex/parsing/source_code.py
zyntex/parsing/source_file.py
zyntex/parsing/source_module.py
zyntex/parsing/bindings/__init__.py
zyntex/parsing/bindings/ast_node.py
zyntex/parsing/bindings/enums.py
zyntex/parsing/bindings/native.py
zyntex/parsing/bindings/structures.py
zyntex/parsing/bindings/translation_unit.py
zyntex/parsing/bindings/native/clib.dll
zyntex/parsing/bindings/native/clib.dylib
zyntex/parsing/bindings/native/clib.so
zyntex/parsing/syntax/__init__.py
zyntex/parsing/syntax/function_declaration.py
zyntex/parsing/syntax/lazy_init.py
zyntex/parsing/syntax/node_element.py
zyntex/parsing/syntax/test_declaration.py
zyntex/parsing/syntax/type_node.py
zyntex/parsing/syntax/variable_declaration.py
zyntex-0.2.3.dist-info/licenses/LICENSE
zyntex-0.2.3.dist-info/METADATA
zyntex-0.2.3.dist-info/WHEEL
zyntex-0.2.3.dist-info/top_level.txt
zyntex-0.2.3.dist-info/RECORD
