Metadata-Version: 2.4
Name: zyntex
Version: 0.2.3
Summary: A high-level Python package to parse and generate Zig code.
Home-page: https://github.com/xXenvy/zyntex
Author: xXenvy
License: MIT
Project-URL: Source, https://github.com/xXenvy/zyntex
Project-URL: Tracker, https://github.com/xXenvy/zyntex/issues
Keywords: zig parser codegen
Classifier: Development Status :: 3 - Alpha
Classifier: Intended Audience :: Developers
Classifier: Programming Language :: Python :: 3
Classifier: Programming Language :: Python :: 3.9
Classifier: Programming Language :: Python :: 3.10
Classifier: Programming Language :: Python :: 3.11
Classifier: Programming Language :: Python :: 3.12
Classifier: Programming Language :: Python :: 3.13
Classifier: Topic :: Software Development :: Compilers
Classifier: Topic :: Software Development :: Libraries
Requires-Python: >=3.9
License-File: LICENSE
Dynamic: author
Dynamic: classifier
Dynamic: description
Dynamic: description-content-type
Dynamic: home-page
Dynamic: keywords
Dynamic: license
Dynamic: license-file
Dynamic: project-url
Dynamic: requires-python
Dynamic: summary
